Metadata-Version: 2.1
Name: regression-testing
Version: 0.7
Summary: UNKNOWN
Home-page: UNKNOWN
Author: Alex Tang
Author-email: at5604@nyu.edu
License: UNKNOWN
Platform: UNKNOWN
Requires-Dist: appdirs (==1.4.4)
Requires-Dist: gitpython (==3.1.37)
Requires-Dist: idna (==3.4)
Requires-Dist: install (==1.3.5)
Requires-Dist: cffi
Requires-Dist: pandas (==2.1.1)
Requires-Dist: pathtools (==0.1.2)
Requires-Dist: pip (==23.2.1)
Requires-Dist: protobuf (==4.24.3)
Requires-Dist: psutil (==5.9.5)
Requires-Dist: pytz (==2023.3.post1)
Requires-Dist: pyyaml (==6.0.1)
Requires-Dist: requests (==2.31.0)
Requires-Dist: sentry-sdk (==1.31.0)
Requires-Dist: setproctitle (==1.3.2)
Requires-Dist: setuptools (==68.0.0)
Requires-Dist: smmap (==5.0.1)
Requires-Dist: tzdata (==2023.3)
Requires-Dist: urllib3 (==2.0.6)
Requires-Dist: wandb (==0.15.11)
Requires-Dist: wheel (==0.41.2)
